ponarize_api/__init__.py
ponarize_api/client.py
ponarize_api-0.7.dist-info/METADATA
ponarize_api-0.7.dist-info/WHEEL
ponarize_api-0.7.dist-info/top_level.txt
ponarize_api-0.7.dist-info/RECORD
