Metadata-Version: 2.1
Name: ponarize-api
Version: 0.7
Summary: Relevant, accurate and fast classification of Domains. Blacklist control for aggressive IPs.
Author: PonaTech
Author-email: info@pona.com.tr
Keywords: We Categorize the Web,api for website,api from website,api key for website,logo api,banking logo api,company logo api,api key website,api of a website,api of website,best api for website,create an api for a website,create an api for your website,Website Category API,Website Logo API,logo api,URL logo api,Webshrinker,classifies a site into a category,zvelo,brandfetch,url categorization,url category check api,website category lookup,web categories,url classification dataset
